nosqlapi/__init__.py
nosqlapi/columndb/__init__.py
nosqlapi/columndb/client.py
nosqlapi/columndb/client.pyi
nosqlapi/columndb/odm.py
nosqlapi/columndb/odm.pyi
nosqlapi/common/__init__.py
nosqlapi/common/core.py
nosqlapi/common/core.pyi
nosqlapi/common/exception.py
nosqlapi/common/odm.py
nosqlapi/common/odm.pyi
nosqlapi/common/utils.py
nosqlapi/common/utils.pyi
nosqlapi/docdb/__init__.py
nosqlapi/docdb/client.py
nosqlapi/docdb/client.pyi
nosqlapi/docdb/odm.py
nosqlapi/docdb/odm.pyi
nosqlapi/graphdb/__init__.py
nosqlapi/graphdb/client.py
nosqlapi/graphdb/client.pyi
nosqlapi/graphdb/odm.py
nosqlapi/graphdb/odm.pyi
nosqlapi/kvdb/__init__.py
nosqlapi/kvdb/client.py
nosqlapi/kvdb/client.pyi
nosqlapi/kvdb/odm.py
nosqlapi/kvdb/odm.pyi
nosqlapi-1.0.2.dist-info/LICENSE.md
nosqlapi-1.0.2.dist-info/METADATA
nosqlapi-1.0.2.dist-info/WHEEL
nosqlapi-1.0.2.dist-info/top_level.txt
nosqlapi-1.0.2.dist-info/RECORD
