Metadata-Version: 2.1
Name: nosqlapi
Version: 1.0.2
Summary: nosqlapi is a library for building standard NOSQL python libraries.
Home-page: https://github.com/MatteoGuadrini/nosqlapi
Author: Matteo Guadrini
Author-email: matteo.guadrini@hotmail.it
Maintainer: Matteo Guadrini
Maintainer-email: matteo.guadrini@hotmail.it
License: GNU General Public License v3.0
Platform: UNKNOWN
Classifier: Programming Language :: Python :: 3
Classifier: Programming Language :: Python :: 3 :: Only
Classifier: License :: OSI Approved :: GNU General Public License v3 (GPLv3)
Classifier: Operating System :: OS Independent
Classifier: Development Status :: 5 - Production/Stable
Classifier: Topic :: Database
Classifier: Topic :: Database :: Database Engines/Servers
Classifier: Topic :: Database :: Front-Ends
Classifier: Topic :: Software Development :: User Interfaces
Classifier: Typing :: Stubs Only
Requires-Python: >=3.6
License-File: LICENSE.md
